tma_saml/__init__.py
tma_saml/exceptions.py
tma_saml/tma_saml.py
tma_saml/user_type.py
tma_saml/for_tests/__init__.py
tma_saml/for_tests/cert_and_key.py
tma_saml/for_tests/fixtures.py
tma_saml/for_tests/flask_test_server.py
tma_saml-0.4.2.dist-info/METADATA
tma_saml-0.4.2.dist-info/WHEEL
tma_saml-0.4.2.dist-info/top_level.txt
tma_saml-0.4.2.dist-info/RECORD
